dynamic_segment_tree/__init__.py
dynamic_segment_tree/_dseg.cpython-313-darwin.so
dynamic_segment_tree-0.1.0.dist-info/METADATA
dynamic_segment_tree-0.1.0.dist-info/WHEEL
dynamic_segment_tree-0.1.0.dist-info/top_level.txt
dynamic_segment_tree-0.1.0.dist-info/RECORD
