Metadata-Version: 2.4
Name: dynamic-segment-tree
Version: 0.1.0
Summary: Dynamic segment tree with Python bindings
Author: Abdullah Enes Oncu
Author-email: abdullahenesoncu@gmail.com
Classifier: Programming Language :: Python :: 3
Classifier: Programming Language :: C++
Classifier: License :: OSI Approved :: MIT License
Classifier: Operating System :: OS Independent
Requires-Python: >=3.7
Requires-Dist: pybind11>=2.6.0
Dynamic: author
Dynamic: author-email
Dynamic: classifier
Dynamic: description
Dynamic: description-content-type
Dynamic: requires-dist
Dynamic: requires-python
Dynamic: summary
